{
  "title": "Best Standing Desks | Curated Comparison | ijustwantto.live",
  "description": "Compare the best standing desks. We evaluate height range, stability, programmable presets, build quality, and price to help you find your perfect workspace.",
  "canonical": "https://ijustwantto.live/list-standing-desks",
  "schemas": [
    [
      {
        "@context": "https://schema.org",
        "@type": "WebApplication",
        "name": "Standing Desk Comparison Tool",
        "url": "https://ijustwantto.live/list-standing-desks.html",
        "applicationCategory": "Utility",
        "operatingSystem": "All",
        "description": "Interactive comparison tool for the best standing desks featuring filterable and sortable data on stability, build quality, and price."
      },
      {
        "@context": "https://schema.org",
        "@type": "Article",
        "headline": "Best Standing Desks: A Comprehensive Comparison",
        "name": "Best Standing Desks",
        "url": "https://ijustwantto.live/list-standing-desks.html",
        "description": "Compare standing desks by height range, stability, programmable presets, build quality, and price.",
        "author": {
          "@type": "Organization",
          "name": "ijustwantto.live"
        },
        "publisher": {
          "@type": "Organization",
          "name": "GAB Ventures"
        }
      }
    ]
  ]
}