{
  "title": "AI Adoption in Canada's Creative Industry (2026 Study)",
  "description": "A comprehensive research study on how Canadian creative agencies, particularly in Montreal, are adopting AI tools like Midjourney and Firefly.",
  "canonical": "https://photonbuilder.com/sites/montrealjobs/ai-adoption-creative-industry-2026",
  "schemas": [
    {
      "@context": "https://schema.org",
      "@type": "Article",
      "headline": "AI Adoption in Canada's Creative Industry (2026 Study)",
      "description": "A deep dive into how AI is reshaping the Canadian creative landscape, with a focus on Montreal. Analyzing tools, hiring impact, and agency pricing models.",
      "author": {
        "@type": "Organization",
        "name": "Montreal Jobs Research"
      },
      "publisher": {
        "@type": "Organization",
        "name": "Montreal Jobs",
        "logo": {
          "@type": "ImageObject",
          "url": "https://photonbuilder.com/favicon.ico"
        }
      },
      "datePublished": "2026-03-15",
      "dateModified": "2026-03-15",
      "mainEntityOfPage": {
        "@type": "WebPage",
        "@id": "https://photonbuilder.com/sites/montrealjobs/ai-adoption-creative-industry-2026"
      }
    }
  ]
}