{
  "pulled": "2026-03-28T11:16:47.321463",
  "site": "sendnerds.photonbuilder.com",
  "period": {
    "start": "2026-02-28",
    "end": "2026-03-28"
  },
  "pages": [
    {
      "path": "/",
      "title": "Send Nerds",
      "sessions": 4,
      "users": 4,
      "pageviews": 4,
      "bounceRate": 1.0,
      "avgDuration": 0.3
    },
    {
      "path": "/",
      "title": "Send Nerds \u2014 Free Academic Calculators & Study Tools",
      "sessions": 4,
      "users": 4,
      "pageviews": 4,
      "bounceRate": 1.0,
      "avgDuration": 0.3
    },
    {
      "path": "/multiplication-chart",
      "title": "Multiplication Chart | Free Printable Times Table 1-20",
      "sessions": 3,
      "users": 2,
      "pageviews": 5,
      "bounceRate": 0.667,
      "avgDuration": 287.1
    }
  ],
  "totalSessions": 11,
  "totalUsers": 10
}