{
  "title": "Expense Ratio Calculator | firemaths.info",
  "description": "Calculate the impact of fund expense ratios on your investment returns over time. Compare the cost of fees between different funds side by side.",
  "canonical": "https://firemaths.info/expense-ratio",
  "schemas": [
    {
      "@context": "https://schema.org",
      "@type": "WebApplication",
      "name": "Expense Ratio Calculator",
      "url": "https://firemaths.info/expense-ratio",
      "description": "Calculate the impact of fund expense ratios on your investment returns over time. Compare the cost of fees between different funds side by side.",
      "applicationCategory": "FinanceApplication",
      "operatingSystem": "All",
      "offers": {
        "@type": "Offer",
        "price": "0",
        "priceCurrency": "USD"
      }
    }
  ]
}