{
  "title": "Sales Tax Calculator | firemaths.info",
  "description": "Easily calculate sales tax for US states and Canadian provinces. Find the exact tax amount and total price with our free, offline-ready calculator.",
  "canonical": "https://firemaths.info/sales-tax",
  "schemas": [
    {
      "@context": "https://schema.org",
      "@type": "WebApplication",
      "name": "Sales Tax Calculator",
      "url": "https://firemaths.info/sales-tax",
      "description": "Calculate sales tax for US states and Canadian provinces. Find the exact tax amount and total price.",
      "applicationCategory": "FinanceApplication",
      "operatingSystem": "All",
      "offers": {
        "@type": "Offer",
        "price": "0",
        "priceCurrency": "USD"
      }
    }
  ]
}